{
  "Sexe": "M",
  "BirthCity": null,
  "BirthCountry": null,
  "DeathCity": null,
  "DeathCountry": null,
  "Comment": null,
  "LastName": "beaudun",
  "MaidenName": null,
  "FirstName": "desire-ii",
  "MiddleName": null,
  "Guid": "fc20f42e-26a2-4c7c-952b-b8bca25d1ce9",
  "FatherGuid": null,
  "MotherGuid": null,
  "CreationDate": {
    "Year": 2004,
    "Month": 1,
    "Day": 24
  },
  "DeathDate": null,
  "BirthDate": null,
  "Images": [
    {
      "ImageName": "BEAUDUN, Desire II",
      "FileName": "BEAUDUN, Desire II.jpg",
      "LocalFileName": "C:\\DVT\\MyGenealogie\\person.db\\beaudun0desire-ii\\BEAUDUN, Desire II.jpg",
      "Url": null
    }
  ]
}