{
  "Sexe": "F",
  "BirthCity": null,
  "BirthCountry": null,
  "DeathCity": null,
  "DeathCountry": null,
  "Comment": null,
  "LastName": "brandis",
  "MaidenName": "constant",
  "FirstName": "therese",
  "MiddleName": null,
  "Guid": "38988206-5ada-421d-9730-8fd0d27773a7",
  "FatherGuid": null,
  "MotherGuid": null,
  "SpouseGuid": null,
  "CreationDate": {
    "Year": 2004,
    "Month": 1,
    "Day": 24
  },
  "DeathDate": null,
  "BirthDate": null,
  "Images": [
    {
      "ImageName": "CONSTANT [BRANDIS], Therese",
      "FileName": "CONSTANT [BRANDIS], Therese.jpg",
      "LocalFileName": "C:\\DVT\\MyGenealogie\\person.db\\constant9brandis0therese\\CONSTANT [BRANDIS], Therese.jpg",
      "Url": "https://mygenealogie.blob.core.windows.net/person-db/CONSTANT [BRANDIS], Therese.jpg"
    }
  ]
}